Workbook

Sheet Pessoa Física
B2: MESES | C2: 46174 | D2: Meio de Pagamento | E2: 46204 | F2: Meio de Pagamento | G2: 46235 | H2: Meio de Pagamento | I2: 46266 | J2: Meio de Pagamento | K2: 46296 | L2: Meio de Pagamento | M2: 46327 | N2: Meio de Pagamento | O2: 46357 | P2: Meio de Pagamento | Q2: 46388 | R2: Meio de Pagamento | S2: 46419 | T2: Meio de Pagamento | U2: 46447 | V2: Meio de Pagamento | W2: 46478 | X2: Meio de Pagamento | Y2: 46508 | Z2: Meio de Pagamento | AA2: TOTAL
B3: DESPESAS
B4: ALIMENTAÇÃO
B5: Supermercado | AA5: =SUM(C5,E5,G5,I5,K5,M5,O5,Q5,S5,U5,W5,Y5)
B6: Feira / Sacolão | AA6: =SUM(C6,E6,G6,I6,K6,M6,O6,Q6,S6,U6,W6,Y6)
B7: Padaria | AA7: =SUM(C7,E7,G7,I7,K7,M7,O7,Q7,S7,U7,W7,Y7)
B8: MORADIA
B9: Prestação / Aluguel de imóvel | AA9: =SUM(C9,E9,G9,I9,K9,M9,O9,Q9,S9,U9,W9,Y9)
B10: Condomínio | AA10: =SUM(C10,E10,G10,I10,K10,M10,O10,Q10,S10,U10,W10,Y10)
B11: Consumo de água | AA11: =SUM(C11,E11,G11,I11,K11,M11,O11,Q11,S11,U11,W11,Y11)
B12: Energia
B13: Internet
B14: EDUCAÇÃO
B15: Matricula Escolar / Mensalidade | AA15: =SUM(C15,E15,G15,I15,K15,M15,O15,Q15,S15,U15,W15,Y15)
B16: Material Escolar | AA16: =SUM(C16,E16,G16,I16,K16,M16,O16,Q16,S16,U16,W16,Y16)
B17: Transporte Escolar | AA17: =SUM(C17,E17,G17,I17,K17,M17,O17,Q17,S17,U17,W17,Y17)
B18: ANIMAL DE ESTIMAÇÃO
B19: Ração | AA19: =SUM(C19,E19,G19,I19,K19,M19,O19,Q19,S19,U19,W19,Y19)
B20: Banho / Tosa | AA20: =SUM(C20,E20,G20,I20,K20,M20,O20,Q20,S20,U20,W20,Y20)
B21: Veterinário | AA21: =SUM(C21,E21,G21,I21,K21,M21,O21,Q21,S21,U21,W21,Y21)
B22: SAÚDE
B23: Plano de Saúde | AA23: =SUM(C23,E23,G23,I23,K23,M23,O23,Q23,S23,U23,W23,Y23)
B24: Medicamentos | AA24: =SUM(C24,E24,G24,I24,K24,M24,O24,Q24,S24,U24,W24,Y24)
B25: Dentista | AA25: =SUM(C25,E25,G25,I25,K25,M25,O25,Q25,S25,U25,W25,Y25)
B26: TRANSPORTE
B27: Ônibus / Metrô | AA27: =SUM(C27,E27,G27,I27,K27,M27,O27,Q27,S27,U27,W27,Y27)
B28: Taxi | AA28: =SUM(C28,E28,G28,I28,K28,M28,O28,Q28,S28,U28,W28,Y28)
B29: Combustível | AA29: =SUM(C29,E29,G29,I29,K29,M29,O29,Q29,S29,U29,W29,Y29)
B30: PESSOAL
B31: Vestuário / Calçados / Acessórios | AA31: =SUM(C31,E31,G31,I31,K31,M31,O31,Q31,S31,U31,W31,Y31)
B32: Cabeleireiro / Manicure / Higiene Pessoal | AA32: =SUM(C32,E32,G32,I32,K32,M32,O32,Q32,S32,U32,W32,Y32)
B33: Presentes | AA33: =SUM(C33,E33,G33,I33,K33,M33,O33,Q33,S33,U33,W33,Y33)
B34: LAZER
B35: Cinema / Teatro / Shows | AA35: =SUM(C35,E35,G35,I35,K35,M35,O35,Q35,S35,U35,W35,Y35)
B36: Livros / Revistas | AA36: =SUM(C36,E36,G36,I36,K36,M36,O36,Q36,S36,U36,W36,Y36)
B37: Viagens | AA37: =SUM(C37,E37,G37,I37,K37,M37,O37,Q37,S37,U37,W37,Y37)
B38: SERVIÇOS FINANCEIROS
B39: Seguros | AA39: =SUM(C39,E39,G39,I39,K39,M39,O39,Q39,S39,U39,W39,Y39)
B40: Investimentos 1 | AA40: =SUM(C40,E40,G40,I40,K40,M40,O40,Q40,S40,U40,W40,Y40)
B41: Investimentos 1 | AA41: =SUM(C41,E41,G41,I41,K41,M41,O41,Q41,S41,U41,W41,Y41)
B42: Imposto de Renda
B43: DÍVIDAS
B44: Dívida 1
B45: Dívida 2
B46: Dívida 3
B47: Total das Despesas | C47: =SUM(C4:C42) | E47: =SUM(E4:E42) | G47: =SUM(G4:G43) | I47: =SUM(I4:I43) | K47: =SUM(K4:K43) | M47: =SUM(M4:M43) | O47: =SUM(O4:O43) | Q47: =SUM(Q4:Q43) | S47: =SUM(S4:S43) | U47: =SUM(U4:U43) | W47: =SUM(W4:W43) | Y47: =SUM(Y4:Y43) | AA47: =SUM(AA5,AA6,AA7,AA9,AA10,AA11,AA15,AA16,AA17,AA19,AA20,AA21,AA23,AA24,AA25,AA27,AA28,AA29,AA31,AA32,AA33,AA35,AA36,AA37,AA39,AA40,AA41,AA43,AA46)
B49: Renda Mensal | C49: 6000 | E49: 6000 | G49: 6000 | I49: 6000 | K49: ='Pessoa Jurídica'!G15 | M49: ='Pessoa Jurídica'!H15 | O49: ='Pessoa Jurídica'!I15 | Q49: ='Pessoa Jurídica'!J15 | S49: ='Pessoa Jurídica'!K15 | U49: ='Pessoa Jurídica'!L15 | W49: ='Pessoa Jurídica'!M15 | Y49: ='Pessoa Jurídica'!N15
B51: Resultado Operacional (renda - despesas) | C51: =SUM(C49-C47) | E51: =SUM(E49-E47) | G51: =SUM(G49-G47) | I51: =SUM(I49-I47) | K51: =SUM(K49-K47) | M51: =SUM(M49-M47) | O51: =SUM(O49-O47) | Q51: =SUM(Q49-Q47) | S51: =SUM(S49-S47) | U51: =SUM(U49-U47) | W51: =SUM(W49-W47) | Y51: =SUM(Y49-Y47)
B53: Investimentos Mensais | C53: =SUM(C40:C41) | E53: =SUM(E40:E41) | G53: =SUM(G40:G41) | I53: =SUM(I40:I41) | K53: =SUM(K40:K41) | M53: =SUM(M40:M41) | O53: =SUM(O40:O41) | Q53: =SUM(Q40:Q41) | S53: =SUM(S40:S41) | U53: =SUM(U40:U41) | W53: =SUM(W40:W41) | Y53: =SUM(Y40:Y41) | AA53: =SUM(C53:Z53)

Sheet Meios de Pagamento
A1: Nome
A2: Cartão de Crédito
A3: Cartão de Débito
A4: Pix
A5: Dinheiro
A6: Boleto
